LICENSE
README.rst
setup.py
BatisX.egg-info/PKG-INFO
BatisX.egg-info/SOURCES.txt
BatisX.egg-info/dependency_links.txt
BatisX.egg-info/not-zip-safe
BatisX.egg-info/requires.txt
BatisX.egg-info/top_level.txt
batisx/__init__.py
batisx/db.py
batisx/dbx.py
batisx/log_support.py
batisx/sql_id_exec.py
batisx/sql_mapper.py
batisx/sql_page_exec.py