Metadata-Version: 2.1
Name: BatisX
Version: 2.2.4
Summary: A easy thread safe sql executor for Python like MyBatis with connection pool. It helps you automatically manage database connections and transactions. Support MySQL, PostgreSQL, SQLite etc.
Home-page: https://gitee.com/summry/batisx
Author: summy
Author-email: xiazhongbiao@126.com
License: UNKNOWN
Keywords: sql,MySQL,PostgreSQL,MyBatis,python
Platform: UNKNOWN
Requires-Python: >=3.5
License-File: LICENSE
